{
  "company_id": "skild_ai",
  "company_name": "Skild AI",
  "hashes": {},
  "history": [
    {
      "execution_date": "2025-10-31",
      "crawled_at": "2025-11-01T21:56:25.933170Z",
      "pages_checked": 0,
      "changes_detected": [],
      "errors": 8
    },
    {
      "execution_date": "2025-11-05",
      "crawled_at": "2025-11-07T00:16:58.984268Z",
      "pages_checked": 0,
      "changes_detected": [],
      "errors": 8
    },
    {
      "execution_date": "2025-11-07",
      "crawled_at": "2025-11-07T00:44:51.305849Z",
      "pages_checked": 0,
      "changes_detected": [],
      "errors": 8
    },
    {
      "execution_date": "2025-11-07",
      "crawled_at": "2025-11-07T01:02:03.758334Z",
      "pages_checked": 0,
      "changes_detected": [],
      "errors": 8
    },
    {
      "execution_date": "2025-11-14",
      "crawled_at": "2025-11-15T23:50:47.739162Z",
      "pages_checked": 0,
      "changes_detected": [],
      "errors": 8
    },
    {
      "execution_date": "2025-11-14",
      "crawled_at": "2025-11-16T00:36:03.604855Z",
      "pages_checked": 0,
      "changes_detected": [],
      "errors": 8
    },
    {
      "execution_date": "2025-11-14",
      "crawled_at": "2025-11-16T03:02:37.282068Z",
      "pages_checked": 0,
      "changes_detected": [],
      "errors": 8
    },
    {
      "execution_date": "2025-11-15",
      "crawled_at": "2025-11-16T03:15:13.633652Z",
      "pages_checked": 0,
      "changes_detected": [],
      "errors": 8
    }
  ]
}